pyproj_dep_analyze/__init__.py
pyproj_dep_analyze/__init__conf__.py
pyproj_dep_analyze/__main__.py
pyproj_dep_analyze/analyzer.py
pyproj_dep_analyze/behaviors.py
pyproj_dep_analyze/cli.py
pyproj_dep_analyze/cli_display.py
pyproj_dep_analyze/config.py
pyproj_dep_analyze/config_deploy.py
pyproj_dep_analyze/config_show.py
pyproj_dep_analyze/defaultconfig.toml
pyproj_dep_analyze/dependency_extractor.py
pyproj_dep_analyze/index_resolver.py
pyproj_dep_analyze/logging_setup.py
pyproj_dep_analyze/models.py
pyproj_dep_analyze/py.typed
pyproj_dep_analyze/python_version_parser.py
pyproj_dep_analyze/repo_resolver.py
pyproj_dep_analyze/schemas.py
pyproj_dep_analyze/stats_resolver.py
pyproj_dep_analyze/version_resolver.py
pyproj_dep_analyze-3.1.0.dist-info/METADATA
pyproj_dep_analyze-3.1.0.dist-info/WHEEL
pyproj_dep_analyze-3.1.0.dist-info/entry_points.txt
pyproj_dep_analyze-3.1.0.dist-info/licenses/LICENSE
pyproj_dep_analyze-3.1.0.dist-info/RECORD
