Metadata-Version: 2.4
Name: pyproj_dep_analyze
Version: 3.1.0
Summary: Python project dependency analyzer
Project-URL: Homepage, https://github.com/bitranox/pyproj_dep_analyze
Project-URL: Repository, https://github.com/bitranox/pyproj_dep_analyze.git
Project-URL: Issues, https://github.com/bitranox/pyproj_dep_analyze/issues
Author-email: bitranox <bitranox@gmail.com>
License: MIT
License-File: LICENSE
Keywords: analyzer,cli,dependency,outdated,pyproject,version
Classifier: Environment :: Console
Classifier: License :: OSI Approved :: MIT License
Classifier: Operating System :: OS Independent
Classifier: Programming Language :: Python :: 3
Classifier: Programming Language :: Python :: 3 :: Only
Classifier: Programming Language :: Python :: 3.10
Classifier: Programming Language :: Python :: 3.11
Classifier: Programming Language :: Python :: 3.12
Classifier: Programming Language :: Python :: 3.13
Classifier: Typing :: Typed
Requires-Python: >=3.10
Requires-Dist: httpx>=0.28.1
Requires-Dist: lib-cli-exit-tools>=2.2.2
Requires-Dist: lib-layered-config>=5.0.0
Requires-Dist: lib-log-rich>=6.0.0
Requires-Dist: pydantic>=2.12.5
Requires-Dist: rich-click>=1.9.4
Requires-Dist: rtoml>=0.13.0
Provides-Extra: dev
Requires-Dist: bandit>=1.9.2; extra == 'dev'
Requires-Dist: build>=1.3.0; extra == 'dev'
Requires-Dist: codecov-cli>=11.2.6; extra == 'dev'
Requires-Dist: import-linter>=2.9; extra == 'dev'
Requires-Dist: pip-audit>=2.10.0; extra == 'dev'
Requires-Dist: pyright>=1.1.407; extra == 'dev'
Requires-Dist: pytest-cov>=7.0.0; extra == 'dev'
Requires-Dist: pytest>=9.0.2; extra == 'dev'
Requires-Dist: ruff>=0.14.9; extra == 'dev'
Requires-Dist: textual>=6.8.0; extra == 'dev'
Requires-Dist: twine>=6.2.0; extra == 'dev'
